CHANGELOG.txt
LICENCE.txt
MANIFEST.in
README.txt
__init__.py
setup.py
TOPSIS_Jaiwant_101803389/topsis.py
TOPSIS_Jaiwant_101803389.egg-info/PKG-INFO
TOPSIS_Jaiwant_101803389.egg-info/SOURCES.txt
TOPSIS_Jaiwant_101803389.egg-info/dependency_links.txt
TOPSIS_Jaiwant_101803389.egg-info/top_level.txt