Metadata-Version: 1.1
Name: TOPSIS-Jaiwant-101803389
Version: 0.0.1
Summary: A very basic  TOPSIS calculator
Home-page: UNKNOWN
Author: Jaiwant Singh
Author-email: jaiwantsingh2000@gmail.com
License: MIT
Keywords: TOPSIS
Platform: UNKNOWN
Classifier: Development Status :: 5 - Production/Stable
Classifier: Intended Audience :: Education
Classifier: Operating System :: Microsoft :: Windows :: Windows 10
Classifier: License :: OSI Approved :: MIT License
Classifier: Programming Language :: Python :: 3
